cryptounifier_python_sdk/BaseAPI.py
cryptounifier_python_sdk/MerchantAPI.py
cryptounifier_python_sdk/WalletAPI.py
cryptounifier_python_sdk/WalletTokenAPI.py
cryptounifier_python_sdk/__init__.py
test/__init__.py
test/merchant-test.py
cryptounifier_python_sdk-0.0.4.dist-info/LICENSE
cryptounifier_python_sdk-0.0.4.dist-info/METADATA
cryptounifier_python_sdk-0.0.4.dist-info/WHEEL
cryptounifier_python_sdk-0.0.4.dist-info/top_level.txt
cryptounifier_python_sdk-0.0.4.dist-info/RECORD
