Metadata-Version: 2.1
Name: cryptounifier-python-sdk
Version: 0.0.4
Summary: CryptoUnifier PYTHON SDK
Author: @h.ben-amara
License: UNKNOWN
Platform: UNKNOWN
Classifier: Programming Language :: Python :: 3
Classifier: License :: OSI Approved :: MIT License
Classifier: Operating System :: OS Independent
Requires-Python: >=3.7
License-File: LICENSE
Requires-Dist: requests
Requires-Dist: attrs
Requires-Dist: urllib3
